{
  "$schema": "http://json-schema.org/draft-04/schema",
  "description": "Push service general response",
  "type": "object",
  "id": "generalResponse",
  "additionalProperties": false,
  "generate-builders": true,
  "properties": {
    "classType": {
      "type": "string",
      "default": "io.openexchange.pojos.api.Response",
      "required": true
    },
    "code": {
      "type": "integer",
      "required": true
    },
    "description": {
      "type": "string",
      "required": true
    }
  }
}